test_package_tlqb/__init__.py
test_package_tlqb/tlqb.py
test_package_tlqb-0.1.4.dist-info/METADATA
test_package_tlqb-0.1.4.dist-info/WHEEL
test_package_tlqb-0.1.4.dist-info/top_level.txt
test_package_tlqb-0.1.4.dist-info/RECORD
