Metadata-Version: 2.1
Name: test-package-tlqb
Version: 0.1.4
Summary: WHAT IS THE REASON YOU BUILD THIS PROJECT AND WHAT IT DOES
Home-page: https://github.com/TLQB/tlqb-tools
Author: tranlequybao
Author-email: tranlequybaotk12@gmail.com
Classifier: Programming Language :: Python :: 3
Classifier: License :: OSI Approved :: Apache Software License
Classifier: Operating System :: OS Independent
Requires-Python: >=3.6
